gs_chunked_io/__init__.py
gs_chunked_io/config.py
gs_chunked_io/reader.py
gs_chunked_io/version.py
gs_chunked_io/writer.py
gs_chunked_io-0.2.12.dist-info/LICENSE
gs_chunked_io-0.2.12.dist-info/METADATA
gs_chunked_io-0.2.12.dist-info/WHEEL
gs_chunked_io-0.2.12.dist-info/top_level.txt
gs_chunked_io-0.2.12.dist-info/RECORD
