Metadata-Version: 2.1
Name: gs-chunked-io
Version: 0.2.12
Summary: Streaming read/writes to Google Storage blobs with ascynchronous buffering.
Home-page: https://github.com/xbrianh/gs-chunked-io.git
Author: Brian Hannafious
Author-email: bhannafi@ucsc.edu
License: MIT
Platform: MacOS X
Platform: Posix
Classifier: Intended Audience :: Developers
Classifier: License :: OSI Approved :: MIT License
Classifier: Programming Language :: Python :: 3.7
Requires-Dist: google-cloud-storage (>=1.26.0)
